sale_price_house_prediction_model/VERSION
sale_price_house_prediction_model/__init__.py
sale_price_house_prediction_model/config.yml
sale_price_house_prediction_model/pipeline.py
sale_price_house_prediction_model/predict.py
sale_price_house_prediction_model/training_pipeline.py
sale_price_house_prediction_model/config/__init__.py
sale_price_house_prediction_model/config/core.py
sale_price_house_prediction_model/datasets/test.csv
sale_price_house_prediction_model/datasets/train.csv
sale_price_house_prediction_model/processing/__init__.py
sale_price_house_prediction_model/processing/data_manager.py
sale_price_house_prediction_model/processing/features.py
sale_price_house_prediction_model/processing/validation.py
sale_price_house_prediction_model/trained_models/sale_price_house_prediction_model_output_v0.0.1.pkl
sale_price_house_prediction_adityalesmana-0.0.1.dist-info/METADATA
sale_price_house_prediction_adityalesmana-0.0.1.dist-info/WHEEL
sale_price_house_prediction_adityalesmana-0.0.1.dist-info/top_level.txt
sale_price_house_prediction_adityalesmana-0.0.1.dist-info/RECORD
